{
  "FormatVersion": "0.20",
  "Header": {
    "DocVersion": "1.309",
    "MinVersionToLoad": "1.309",
    "MSAppStructureVersion": "2.0"
  },
  "Properties": {
    "AppCreationSource": "AppFromData",
    "AppDescription": "",
    "AppPreviewFlagsMap": {
      "aibuilderserviceenrollment": true,
      "autocreateenvironmentvariables": false,
      "backfromhostaction": false,
      "behaviorpropertyui": false,
      "blockmovingcontrol": false,
      "classiccontrols": false,
      "componentauthoring": true,
      "datatablev2control": true,
      "delaycontrolrendering": false,
      "delayloadscreens": true,
      "dynamicschema": false,
      "enableaimodelsindatapane": false,
      "enableappembeddingux": false,
      "enablecdsfileandlargeimage": true,
      "enableonstartnavigate": false,
      "enablepcfmoderndatasets": false,
      "enablerowscopeonetonexpand": false,
      "enablerulespanel": false,
      "enablesummerlandgeospatialfeatures": true,
      "enhanceddelegation": true,
      "enhancedgalleryinitialization": true,
      "enhancedgroupcontrol": true,
      "errorhandling": false,
      "externalmessage": false,
      "formuladataprefetch": false,
      "generatedebugpublishedapp": false,
      "improvedmediacapture": false,
      "keeprecentscreensloaded": false,
      "korenderingstack": false,
      "longlivingcache": false,
      "nativecdsexperimental": true,
      "optimizedforteamsmeeting": false,
      "parallelcodegen": false,
      "projectionmapping": true,
      "reactformulabar": false,
      "reliableconcurrent": true,
      "usedisplaynamemetadata": true,
      "useenforcesavedatalimits": true,
      "useexperimentalcdsconnector": true,
      "useexperimentalsqlconnector": true,
      "useguiddatatypes": true,
      "usenonblockingonstartrule": true,
      "webbarcodescanner": false
    },
    "Author": "",
    "ContainsThirdPartyPcfControls": false,
    "DefaultConnectedDataSourceMaxGetRowsCount": 500,
    "DocumentAppType": "Phone",
    "DocumentLayoutHeight": 1136,
    "DocumentLayoutLockOrientation": true,
    "DocumentLayoutMaintainAspectRatio": true,
    "DocumentLayoutOrientation": "portrait",
    "DocumentLayoutScaleToFit": true,
    "DocumentLayoutWidth": 640,
    "DocumentType": "App",
    "EnableInstrumentation": false,
    "ErrorCount": 0,
    "FileID": "53410274-3a85-4e6b-8c39-5bd5edbfa746",
    "Id": "50527142-88f4-4cec-8ade-8629a54ec164",
    "InstrumentationKey": "",
    "Name": "ModelDrivenAppBasedOnSharePointList.msapp",
    "OriginatingVersion": "1.285"
  },
  "PublishInfo": {
    "AppName": "ModelDrivenAppBasedOnSharePointList",
    "BackgroundColor": "rgba(1, 131, 134, 1)",
    "IconColor": "RGBA(255,255,255,1)",
    "IconName": "Edit",
    "LogoFileName": "logo.jpg",
    "PublishDataLocally": false,
    "PublishResourcesLocally": false,
    "PublishTarget": "player",
    "UserLocale": "pl-PL"
  },
  "ScreenOrder": [
    "BrowseScreen1",
    "DetailScreen1",
    "EditScreen1"
  ]
}